<?xml version="1.0" encoding="UTF-8"?>
<?xml-stylesheet href="hide-it.xsl" type="text/xsl"?>
<item>
	<title>Theres Something In The Barn (2023)</title>
	<link>
	        <sublink>https://rapidgator.net/file/716e39a326bd82b54bbba4fce55762a3/</sublink>
	</link>
	<thumbnail>https://i.imgur.com/rKbVXA7.jpg</thumbnail>
</item>
<item>
	<title>Killers Of The Flower Moon (2023)</title>
	<link>
	        <sublink>https://rapidgator.net/file/c1605258c48604f7eaabe220f5d2c402/</sublink>
		<sublink>https://rapidgator.net/file/df2d9afd10d242edf46e1bdc7274def2</sublink>
	</link>
	<thumbnail>https://i.imgur.com/YqcyrMv.jpg</thumbnail>
</item>
<item>
	<title>Malum (2023)</title>
	<link>
	        <sublink>https://rapidgator.net/file/edcc6fef41b757ab6177c3997d48082f/</sublink>
	</link>
	<thumbnail>https://i.imgur.com/Qu1fhnN.jpg</thumbnail>
</item>
<item>
	<title>Scrapper (2023)</title>
	<link>
	        <sublink>https://rapidgator.net/file/ed6258dc055b674b13857374e859a764</sublink>
	</link>
	<thumbnail>https://i.imgur.com/NXupl4D.jpg</thumbnail>
</item>
<item>
	<title>The Shepherd (2023)</title>
	<link>
	        <sublink>https://rapidgator.net/file/489004a7c358a093d1bf6682f96b8cc8</sublink>
	</link>
	<thumbnail>https://i.imgur.com/eTJ1Hwz.jpg</thumbnail>
</item>
<item>
	<title>Bad CGI Gator (2023)</title>
	<link>
	        <sublink>https://rapidgator.net/file/515080afffe38f993fd4e23085e5d2fd/</sublink>
	</link>
	<thumbnail>https://i.imgur.com/4hArHGo.jpg</thumbnail>
</item>
<item>
	<title>May December (2023)</title>
	<link>
	        <sublink>https://rapidgator.net/file/d17b682ea85ebae22d0c9c1271fe66fd/</sublink>
	        <sublink>https://rapidgator.net/file/d7fb3b4b1862a72d1028e22ec87292ed/</sublink>
	</link>
	<thumbnail>https://i.imgur.com/oFoLF9H.jpg</thumbnail>
</item>
<item>
	<title>How the Gringo Stole Christmas (2023)</title>
	<link>
	        <sublink>https://rapidgator.net/file/4b1a1d609a9ce274c1c1032a62cc94c4/</sublink>
	</link>
	<thumbnail>https://i.imgur.com/AyyfE25.jpg</thumbnail>
</item>
<item>
	<title>It's a Wonderful Knife (2023)</title>
	<link>
	        <sublink>https://rapidgator.net/file/ef961bc691b1ecdaea11c56cad89d81e</sublink>
	        <sublink>https://rapidgator.net/file/fd428118277d1c99a67252da8791721b/</sublink>
	</link>
	<thumbnail>https://i.imgur.com/27yEUnL.jpg</thumbnail>
</item>
<item>
	<title>Candy Cane Lane (2023)</title>
	<link>
	        <sublink>https://rapidgator.net/file/e4cf0f3dce6272deafcb1748a943d234</sublink>
	        <sublink>https://rapidgator.net/file/0968aa24fd594eff49152f1aefe45ff7/</sublink>
	</link>
	<thumbnail>https://i.imgur.com/FXkWdRE.jpg</thumbnail>
</item>
<item>
	<title>Family Switch (2023)</title>
	<link>
	<sublink>https://rapidgator.net/file/43b3c5ab4531c9aaecaf84b471dd5103/</sublink>
	<sublink>https://rapidgator.net/file/4054c3c37bcfffb10131c1c502e1b0f5/</sublink>
	</link>
	<thumbnail>https://i.imgur.com/6ieVBKG.jpg</thumbnail>
</item>
<item>
	<title>Woman In The Maze (2023)</title>
	<link>
	<sublink>https://rapidgator.net/file/e25161fc4aa7c60940f9d419d6c5464a/</sublink>
	<sublink>https://rapidgator.net/file/d977b01634c798ad002b4df121a9b78c/</sublink>
	</link>
	<thumbnail>https://i.imgur.com/yzVAWVP.jpg</thumbnail>
</item>
<item>
	<title>Kane (2023)</title>
	<link>
	<sublink>https://rapidgator.net/file/384b1d73343c605e18062bc8dfc4af26</sublink>
	<sublink>https://rapidgator.net/file/67f6486ed8e51bdfc1e9f49df04e07d3/</sublink>
	</link>
	<thumbnail>https://i.imgur.com/2xENBuq.jpg</thumbnail>
</item>
<item>
	<title>Wintertide (2023)</title>
	<link>
	<sublink>https://rapidgator.net/file/0d1dd945c466fe11af7f3f4459bf3527/</sublink>
	</link>
	<thumbnail>https://i.imgur.com/mjxvryV.jpg</thumbnail>
</item>
<item>
	<title>Unstoppable Taylor Swift (2023)</title>
	<link>
	<sublink>https://rapidgator.net/file/176231e257a397285588b462f398cb0c/</sublink>
	</link>
	<thumbnail>https://i.imgur.com/mvfpNN1.jpg</thumbnail>
</item>
<item>
	<title>Night Of The Missing (2023)</title>
	<link>
	<sublink>https://rapidgator.net/file/2e90bbed6697de7699673c2024ba98db/</sublink>
	</link>
	<thumbnail>https://i.imgur.com/gnPesMA.jpg</thumbnail>
</item>
<item>
	<title>Youre All Gonna Die (2023)</title>
	<link>
	<sublink>https://rapidgator.net/file/b715c2255ffc3fc41a8766a7a350f311/</sublink>
	</link>
	<thumbnail>https://i.imgur.com/EcnUgKA.jpg</thumbnail>
</item>
<item>
	<title>The Lesson (2023)</title>
	<link>
	<sublink>https://rapidgator.net/file/3b9244fd864fe46ceefd8a9b54678614/</sublink>
	</link>
	<thumbnail>https://i.imgur.com/lMvSDwk.jpg</thumbnail>
</item>
<item>
	<title>Welcome to Redville (2023)</title>
	<link>
	<sublink>https://rapidgator.net/file/08e4de32d9e0da50a16429db75843314</sublink>
	<sublink>https://rapidgator.net/file/c3962c9644445d9537355a0a227713da/</sublink>
	</link>
	<thumbnail>https://i.imgur.com/8rMDTYT.jpg</thumbnail>
</item>
<item>
	<title>The Holdovers (2023)</title>
	<link>
	<sublink>https://rapidgator.net/file/71312fad2810dfb2c0b1a300818f6d1c</sublink>
	<sublink>https://rapidgator.net/file/4c41e28690748be6af9afd12e22657c0/</sublink>
	</link>
	<thumbnail>https://i.imgur.com/XaElo1h.jpg</thumbnail>
</item>
<item>
	<title>What Happens Later (2023)</title>
	<link>
	<sublink>https://rapidgator.net/file/fce6d0a765e004311ff3d163276e2df8</sublink>
	<sublink>https://rapidgator.net/file/1637e238cbb289d1584c4f4aa91ec2ce/</sublink>
	</link>
	<thumbnail>https://i.imgur.com/NtFl8pw.jpg</thumbnail>
</item>
<item>
	<title>Freelance (2023)</title>
	<link>
	<sublink>https://rapidgator.net/file/0f9e15b617dac0d5e17c03f19b08b913</sublink>
	<sublink>magnet:?xt=urn:btih:6cc0ef43e986214568ca56c534feecfcd280d964&dn=Freelance.2023.1080p.WEBRip.1400MB.DD5.1.x264-GalaxyRG</sublink>
	</link>
	<thumbnail>https://i.imgur.com/MQR7vT5.jpg</thumbnail>
</item>
<item>
	<title>In the Land of Saints and Sinners (2023)</title>
	<link>
	<sublink>https://rapidgator.net/file/2f63ce333bef1dfe08423514c29fd5bc</sublink>
	<sublink>magnet:?xt=urn:btih:9ebf4553948bc5c7182429233d7666fec4d1d5d5&dn=In.The.Land.Of.Saints.And.Sinners.2023.1080p.WEBRip.1400MB.DD5.1.x264-GalaxyRG</sublink>
	</link>
	<thumbnail>https://i.imgur.com/iB7gSQq.jpg</thumbnail>
</item>
<item>
	<title>The Three Musketeers (2023)</title>
	<link>
	<sublink>https://rapidgator.net/file/2f0a00bc5c752aae7fb882ceab5164b3/</sublink>
	</link>
	<thumbnail>https://i.imgur.com/Fe2G8Nz.jpg</thumbnail>
</item>
<item>
	<title>Obi-Wan Kenobi (2022)</title>
	<link>
	<sublink>magnet:?xt=urn:btih:7DA0C3DC8BEF3DAC9D8975652D40224C37D713AA&dn=Obi-Wan+Kenobi+%282022%29+%5B1080p%5D+%5BYTS.MX%5D</sublink>
	</link>
	<thumbnail>https://i.imgur.com/5lHVsWs.jpg</thumbnail>
</item>
<item>
	<title>The Dive (2023)</title>
	<link>
	<sublink>https://rapidgator.net/file/cfadebb4a2ecec783890462ff5fa88d1/</sublink>
	</link>
	<thumbnail>https://i.imgur.com/ilan67E.jpg</thumbnail>
</item>
<item>
	<title>River Wild (2023)</title>
	<link>
	<sublink>https://rapidgator.net/file/bd4ae0ab62697de8c725523522479424/</sublink>
	</link>
	<thumbnail>https://i.imgur.com/rarCKzl.jpg</thumbnail>
</item>
<item>
	<title>The Naughty Nine (2023)</title>
	<link>
	<sublink>https://rapidgator.net/file/58d62342aa41497a0bafc74fd29ee4d9</sublink>
	<sublink>magnet:?xt=urn:btih:62e56cdaf789a93f4f4ec57e9c42119918df1642&dn=The.Naughty.Nine.2023.1080p.DSNP.WEBRip.1400MB.DD5.1.x264-GalaxyRG</sublink>
	</link>
	<thumbnail>https://i.imgur.com/a1cDtaV.jpg</thumbnail>
</item>
<item>
	<title>Zombie Town (2023)</title>
	<link>
	<sublink>https://rapidgator.net/file/eacbaf75befe6682664be4604d60a4a1</sublink>
	<sublink>magnet:?xt=urn:btih:1b521d215b4ea1aab060d3c68af50fbddce3756c&dn=Zombie.Town.2023.1080p.WEBRip.DDP5.1.x265.10bit-GalaxyRG265</sublink>
	</link>
	<thumbnail>https://i.imgur.com/SNex6Vg.jpg</thumbnail>
</item>
<item>
	<title>Good Burger 2 (2023)</title>
	<link>
	<sublink>https://rapidgator.net/file/dba0011eff8526ff6115dc74f016aa7a</sublink>
	<sublink>magnet:?xt=urn:btih:1ae0a78f03bbfade2c431ef8a1bf3e22cbb86e0a&dn=Good.Burger.2.2023.1080p.AMZN.WEBRip.1400MB.DD5.1.x264-GalaxyRG</sublink>
	</link>
	<thumbnail>https://i.imgur.com/7VF7ENf.jpg</thumbnail>
</item>
<item>
	<title>Back on the Strip (2023)</title>
	<link>
	<sublink>https://rapidgator.net/file/21452c9a72c542bf5c480ca4091ae6b0</sublink>
	<sublink>magnet:?xt=urn:btih:539ce0ac5f39ca03f8e50a687ff1a6df9314e50d&dn=Back.on.the.Strip.2023.1080p.AMZN.WEBRip.DDP5.1.x265.10bit-GalaxyRG265</sublink>
	</link>
	<thumbnail>https://i.imgur.com/4Ogfk1G.jpg</thumbnail>
</item>
<item>
	<title>The Marsh King's Daughter (2023)</title>
	<link>
	<sublink>https://rapidgator.net/file/b73be8698f8c8d589f28cd7aa800ac0f/</sublink>
	<sublink>magnet:?xt=urn:btih:bafabfb560dcfa20406639145dbe06321530ea77&dn=The.Marsh.Kings.Daughter.2023.1080p.WEBRip.1400MB.DD5.1.x264-GalaxyRG</sublink>
	</link>
	<thumbnail>https://i.imgur.com/eP5UM49.jpg</thumbnail>
</item>
<item>
	<title>Leo (2023)</title>
	<link>
	<sublink>https://rapidgator.net/file/4c10d6229cd4370cb428fe0cace424af/</sublink>
	<sublink>magnet:?xt=urn:btih:13d9dd78520fb52204d837c179769b67c8e9c27a&dn=Leo.2023.1080p.WEBRip.1400MB.DD5.1.x264-GalaxyRG</sublink>
	</link>
	<thumbnail>https://i.imgur.com/gGopxjL.jpg</thumbnail>
</item>
<item>
	<title>Sick Girl (2023)</title>
	<link>
	<sublink>https://rapidgator.net/file/6e0c6eb379af9bb15832bbb33e4c5ff5</sublink>
	<sublink>magnet:?xt=urn:btih:b02e3aa6f57c0d8e37a1e728e2b5e131c5606ea9&dn=Sick.Girl.2023.1080p.WEBRip.DDP5.1.x265.10bit-GalaxyRG265</sublink>
	</link>
	<thumbnail>https://i.imgur.com/rqSLE01.jpg</thumbnail>
</item>
<item>
	<title>Break In (2023)</title>
	<link>
	<sublink>magnet:?xt=urn:btih:0AE6E82DD723895AF2508D909E07E93D9F651801&dn=Break+In+%282023%29+%5B1080p%5D+%5BYTS.MX%5D</sublink>
	</link>
	<thumbnail>https://i.imgur.com/0k8TkbQ.jpg</thumbnail>
</item>
<item>
	<title>R.A.D.A.R.: The Adventures of the Bionic Dog (2023)</title>
	<link>
	<sublink>magnet:?xt=urn:btih:1070EBB32FEF57F9C7EACF8C645BB872DFBE9FA2&dn=R.A.D.A.R.%3A+The+Adventures+of+the+Bionic+Dog+%282023%29+%5B1080p%5D+%5BYTS.MX%5D</sublink>
	</link>
	<thumbnail>https://i.imgur.com/o8HtB7J.jpg</thumbnail>
</item>
<item>
	<title>Trolls Band Together (2023)</title>
	<link>
	<sublink>https://rapidgator.net/file/c08829b5e8d1f2da98ae069bb838c969</sublink>
	<sublink>magnet:?xt=urn:btih:212621992f5105a00a35a291772a8287c7becb67&dn=Trolls.Band.Together.2023.1080p.AMZN.WEB-DL.DDP5.1.Atmos.H.264-FLUX[TGx]</sublink>
	</link>
	<thumbnail>https://i.imgur.com/tYXtTKf.jpg</thumbnail>
</item>
<item>
	<title>Where the Devil Roams (2023)</title>
	<link>
	<sublink>magnet:?xt=urn:btih:72841D0033A30F9E674B704EB27DBB96BD83F969&dn=Where+the+Devil+Roams+%282023%29+%5B1080p%5D+%5BYTS.MX%5D</sublink>
	</link>
	<thumbnail>https://i.imgur.com/WMbFKoV.jpg</thumbnail>
</item>
<item>
	<title>Please Don't Destroy: The Treasure of Foggy Mountain (2023)</title>
	<link>
	<sublink>https://rapidgator.net/file/80a9684f6f07d793e491a83a4e44d8a0</sublink>
	<sublink>magnet:?xt=urn:btih:5487c560bd15610bcec4e84866e8da896dee850e&dn=Please.Dont.Destroy.The.Treasure.of.Foggy.Mountain.2023.1080p.PCOK.WEB-DL.DDP5.1.H.264-FLU...</sublink>
	</link>
	<thumbnail>https://i.imgur.com/ibAaxZc.jpg</thumbnail>
</item>
<item>
	<title>Dashing Through the Snow (2023)</title>
	<link>
	<sublink>https://rapidgator.net/file/a6c329daafda25100caf6ce2338a7213</sublink>
	<sublink>magnet:?xt=urn:btih:08dbdb56231ec0193db2f888cd5e47150155a7d2&dn=Dashing.Through.the.Snow.2023.1080p.DSNP.WEB-DL.DDP5.1.Atmos.H.264-FLUX[TGx]</sublink>
        </link>    
	<thumbnail>https://i.imgur.com/VNfmgqF.jpg</thumbnail>
</item>
<item>
	<title>Johnny Z (2023)</title>
	<link>
	<sublink>https://rapidgator.net/file/a63c2852c432badeba7ee28454514b49/</sublink>
	</link>
	<thumbnail>https://i.imgur.com/ESOTbsL.jpg</thumbnail>
</item>
<item>
	<title>Rustin (2023)</title>
	<link>
	<sublink>magnet:?xt=urn:btih:06EA46F7ABE289705E388EB69AA82BABF3F85542&dn=Rustin+%282023%29+%5B1080p%5D+%5BYTS.MX%5D</sublink>
	</link>
	<thumbnail>https://i.imgur.com/gMaEYNU.jpg</thumbnail>
</item>
<item>
	<title>Payment Received (2023)</title>
	<link>
	<sublink>magnet:?xt=urn:btih:F9AF2D95D42030E9626F949D1543E948DEFC1C00&dn=Payment+Received+%282023%29+%5B1080p%5D+%5BYTS.MX%5D</sublink>
	</link>
	<thumbnail>https://i.imgur.com/RBiOLt1.jpg</thumbnail>
</item>
<item>
	<title>It Be An Evil Moon (2023)</title>
	<link>
	<sublink>https://rapidgator.net/file/931d5584f6bed415f5445f4cb67375e1/</sublink>
	</link>
	<thumbnail>https://i.imgur.com/EmKtzpr.jpg</thumbnail>
</item>
<item>
	<title>Manodrome (2023)</title>
	<link>
	<sublink>https://rapidgator.net/file/ad431c9abec531a697674d7c1966365c</sublink>
	<sublink>https://rapidgator.net/file/8568d676ebffd0b385c7f6bc4840b086/</sublink>
	</link>
	<thumbnail>https://i.imgur.com/y49b8fJ.jpg</thumbnail>
</item>
<item>
	<title>Black Noise (2023)</title>
	<link>
	<sublink>magnet:?xt=urn:btih:ad09d13f3ce816d769f1039bd92e1c7fc5079000&dn=Black.Noise.2023.1080p.WEBRip.1400MB.DD5.1.x264-GalaxyRG</sublink>    
	</link>
	<thumbnail>https://i.imgur.com/f70ojXV.jpg</thumbnail>
</item>
<item>
	<title>It Lives Inside (2023)</title>
	<link>https://rapidgator.net/file/e49e6ba400843b800da7bb3ab19534d0/</link>
	<thumbnail>https://i.imgur.com/6RROqKR.jpg</thumbnail>
</item>
<item>
	<title>Onyx The Fortuitous And The Talisman Of Souls (2023)</title>
	<link>https://rapidgator.net/file/2468631ffb59ae627f05ec9aea02ffa6/</link>
	<thumbnail>https://i.imgur.com/ubBWINg.jpg</thumbnail>
</item>
<item>
	<title>Your Lucky Day (2023)</title>
	<link>
	<sublink>https://rapidgator.net/file/2f91a919a8731f07b42f3f86a83a19bd</sublink>
	<sublink>https://rapidgator.net/file/a727d18a8540c7fe838bf4c75cdf7438/</sublink>    
	</link>
	<thumbnail>https://i.imgur.com/3OXeb3R.jpg</thumbnail>
</item>
<item>
	<title>Miranda's Victim (2023)</title>
	<link>
	<sublink>https://rapidgator.net/file/2e8b9669f4b07ae6dd2705aa02b602f2</sublink>
	<sublink>https://rapidgator.net/file/9161af7a7d702c87fae78324e5a1a2c0/</sublink>    
	</link>
	<thumbnail>https://i.imgur.com/oHulc36.jpg</thumbnail>
</item>
<item>
	<title>Monster Inside Americas Most Extreme Haunted House (2023)</title>
	<link>https://rapidgator.net/file/4774de17d9c15fea353523f50d11bc1c/</link>
	<thumbnail>https://i.imgur.com/MREjiPN.jpg</thumbnail>
</item>
<item>
	<title>Night of the Hunted (2023)</title>
	<link>https://rapidgator.net/file/efaf965bf70a1a8c52a67362f08c1e49/</link>
	<thumbnail>https://i.imgur.com/GTrQgrE.jpg</thumbnail>
</item>
<item>
	<title>The Creator (2023)</title>
	<link>https://rapidgator.net/file/d82842c07f62216a9e13e6cab5a48032</link>
	<thumbnail>https://i.imgur.com/E9ozOuP.jpg</thumbnail>
</item>
<item>
	<title>What Comes Around (2023)</title>
	<link>https://rapidgator.net/file/7101905762a1500af94864622ed8fa67/</link>
	<thumbnail>https://i.imgur.com/Wy25QPh.jpg</thumbnail>
</item>
<item>
	<title>Sound Of Freedom (2023)</title>
	<link>https://rapidgator.net/file/d516ebef5b6bd2c9bab7107568a1ba37/</link>
	<thumbnail>https://i.imgur.com/bbD26ja.jpg</thumbnail>
</item>
<item>
	<title>A Little White Lie (2023)</title>
	<link>magnet:?xt=urn:btih:D3E4A235BF431DF401E275CA9423E7AAB7772328&dn=A+Little+White+Lie+%282023%29+%5B1080p%5D+%5BYTS.MX%5D</link>
	<thumbnail>https://i.imgur.com/F08wiJZ.jpg</thumbnail>
</item>
<item>
	<title>Cocaine Shark (2023)</title>
	<link>
	<sublink>https://rapidgator.net/file/ee2222d1d3293f1529ec815d90521009/</sublink> 
	</link>
	<thumbnail>https://i.imgur.com/DvKqMGI.jpg</thumbnail>
</item>
<item>
	<title>The Killer (2023)</title>
	<link>
	<sublink>https://rapidgator.net/file/e7fc7dbbb2974a100c418487085b1e97/</sublink>
	<sublink>magnet:?xt=urn:btih:B8AAC15138B2D2C67DB8B59415D6E34226EF7471&dn=The+Killer+%282023%29+%5B1080p%5D+%5BYTS.MX%5D</sublink>    
	</link>
	<thumbnail>https://i.imgur.com/6vWCwfp.jpg</thumbnail>
</item>
<item>
	<title>Rumble Through the Dark (2023)</title>
	<link>
	<sublink>https://rapidgator.net/file/7d447009fe9a119fb88d6fa18a2bbae2/</sublink>
	<sublink>https://rapidgator.net/file/3f38beeb50f2274dbd4f044c23f8439c</sublink>    
	</link>
	<link>https://rapidgator.net/file/3f38beeb50f2274dbd4f044c23f8439c</link>
	<thumbnail>https://i.imgur.com/j5kthzC.jpg</thumbnail>
</item>
<item>
	<title>Dicks: The Musical (2023)</title>
	<link>
	<sublink>https://rapidgator.net/file/83684140b4d1ecad56e5b19291b3674f/</sublink>
	<sublink>https://rapidgator.net/file/53a48f22eb83e3c4c22a23a892941ee0</sublink>    
	</link>
	<thumbnail>https://i.imgur.com/rqY7TOq.jpg</thumbnail>
</item>
<item>
	<title>Death on the Border (2023)</title>
	<link>
	<sublink>https://rapidgator.net/file/f6fa38d4db04938a61760df2189eaf8d</sublink>
	<sublink>magnet:?xt=urn:btih:4cf94fe83613a11b33b7f9d1fe695aeaaadcd5c7&dn=Death.On.The.Border.2023.1080p.AMZN.WEBRip.1400MB.DD5.1.x264-GalaxyRG</sublink>    
	</link>
	<thumbnail>https://i.imgur.com/Y73T8QW.jpg</thumbnail>
</item>
<item>
	<title>Oppenheimer (2023)</title>
	<link>
	<sublink>https://rapidgator.net/file/48bcdcedc8d938fa208c76060747da2d</sublink>
	<sublink>magnet:?xt=urn:btih:491aa0e19cbdb03b100961db82315c08643a6139&dn=Oppenheimer.2023.1080p.BluRay.2GB.DD5.1.x264-GalaxyRG</sublink>    
	</link>
	<thumbnail>https://i.imgur.com/PRsxxBc.jpg</thumbnail>
</item>
<item>
	<title>The Blind (2023)</title>
	<link>
	<sublink>https://rapidgator.net/file/591f27164d835a807bd968028956eb51</sublink>
	<sublink>magnet:?xt=urn:btih:807121eef4b11fa7ee1fda7a85825a25e6e0c7e7&dn=The.Blind.2023.1080p.AMZN.WEBRip.1400MB.DD5.1.x264-GalaxyRG</sublink>    
	</link>
	<thumbnail>https://i.imgur.com/0o8eNmE.jpg</thumbnail>
</item>
<item>
	<title>Foe (2023)</title>
	<link>
	<sublink>https://rapidgator.net/file/14e2a22c089dfb5beb7332cbd435268e</sublink>
	<sublink>magnet:?xt=urn:btih:4afcf55d25382367b69b2e04157e49f808665a39&dn=Foe.2023.1080p.WEBRip.1400MB.DD5.1.x264-GalaxyRG</sublink>    
	</link>
	<thumbnail>https://i.imgur.com/pmSAIs0.jpg</thumbnail>
</item>
<item>
	<title>She Came to Me (2023)</title>
	<link>
	<sublink>https://rapidgator.net/file/ac3b7b5ea55eef5ed918118cdcf0148b/</sublink>
	<sublink>magnet:?xt=urn:btih:9D2E30B4BFB37B607872DE1BD6F4302D3E34BC37&dn=She.Came.to.Me.2023.1080p.AMZN.WEB-DL.DDP5.1.H.264-FLUX.torrent</sublink>    
	</link>
	<thumbnail>https://i.imgur.com/7j3BG0s.jpg</thumbnail>
</item>
<item>
	<title>The Equalizer 3 (2023)</title>
	<link>https://rapidgator.net/file/9ea587650b0e443e7db5c067ed1a781f/</link>
	<thumbnail>https://i.imgur.com/z00p3cQ.jpg</thumbnail>
</item>
<item>
	<title>Dumb Money (2023)</title>
	<link>
	<sublink>https://rapidgator.net/file/b45a1510480c3bd284e8549a7073da90/</sublink>
	<sublink>magnet:?xt=urn:btih:8F2E12306FE67C8860038ECED6A59CD45F0D8FE6&dn=Dumb+Money+%282023%29+%5B1080p%5D+%5BYTS.MX%5D</sublink>    
	</link>
	<thumbnail>https://i.imgur.com/r1HIhm7.jpg</thumbnail>
</item>
<item>
	<title>Under the Boardwalk (2023)</title>
	<link>
	<sublink>https://rapidgator.net/file/8d19ad737f32d74eff7dfc9d2cee2eb9/</sublink>
	<sublink>magnet:?xt=urn:btih:8bc87026e3ae976924416a056d12ea779c92e575&dn=Under.The.Boardwalk.2023.1080p.AMZN.WEBRip.1400MB.DD5.1.x264-GalaxyRG</sublink>    
	</link>
	<thumbnail>https://i.imgur.com/foKe4AR.jpg</thumbnail>
</item>
<item>
	<title>The Magnificent Meyersons (2023)</title>
	<link>magnet:?xt=urn:btih:90a53f66d3128f0d912f16620d851cd030414082&dn=The.Magnificent.Meyersons.2023.1080p.WEBRip.1400MB.DD5.1.x264-GalaxyRG</link>
	<thumbnail>https://i.imgur.com/GXGq4cs.jpg</thumbnail>
</item>
<item>
	<title>The Great Escaper (2023)</title>
	<link>
	<sublink>https://rapidgator.net/file/81e8cdb45f177fa1ca4af2126d47153f/</sublink>
	<sublink>magnet:?xt=urn:btih:396b50d21635153a626f0c1e6c2e9cdecead1a0f&dn=The.Great.Escaper.2023.1080p.WEB-DL.DDP5.1.H264-AOC[TGx]</sublink>    
	</link>
	<thumbnail>https://i.imgur.com/LXkPjZE.jpg</thumbnail>
</item>
<item>
	<title>The Last Rifleman (2023)</title>
	<link>magnet:?xt=urn:btih:A8EC55C340D5C2C9B8E4FE6CFAD2414685CA4ADF&dn=The+Last+Rifleman+%282023%29+%5B1080p%5D+%5BYTS.MX%5D</link>
	<thumbnail>https://i.imgur.com/FZyyB1s.jpg</thumbnail>
</item>
<item>
	<title>Ape vs. Mecha Ape (2023)</title>
	<link>https://rapidgator.net/file/61a5630972f707290ec6c8273f398938/</link>
	<thumbnail>https://i.imgur.com/Ip9unSn.jpg</thumbnail>
</item>
<item>
	<title>The Madness (2023)</title>
	<link>https://rapidgator.net/file/e85badf863d9b3ced79d5b008e82a85e/</link>
	<thumbnail>https://i.imgur.com/gpQpR1w.jpg</thumbnail>
</item>
<item>
	<title>The Headmistress (2023)</title>
	<link>https://rapidgator.net/file/c714a9b59ae7664426da9d9c929083d8/</link>
	<thumbnail>https://i.imgur.com/96WkTVk.jpg</thumbnail>
</item>
<item>
	<title>Hell Of The Screaming Undead (2023)</title>
	<link>https://rapidgator.net/file/56af35845c94a58921f3ae2758ef070d/</link>
	<thumbnail>https://i.imgur.com/zElbEf6.jpg</thumbnail>
</item>
<item>
	<title>Dr Savilles Horror Show (2023)</title>
	<link>https://rapidgator.net/file/6e58ea4a2a72ac757b0a0e862515ac49/</link>
	<thumbnail>https://i.imgur.com/iPliOgJ.jpg</thumbnail>
</item>
<item>
	<title>Nyad (2023)</title>
	<link>magnet:?xt=urn:btih:fac999357da574819f7b5308444b7946ab4fe4b5&dn=NYAD.2023.1080p.WEB.H264-AccomplishedYak[TGx]</link>
	<thumbnail>https://i.imgur.com/M2CvUWm.jpg</thumbnail>
</item>
<item>
	<title>Richard The Stork And The Mystery Of The Great Jewel (2023)</title>
	<link>https://rapidgator.net/file/d3093d69371d0b28142268fa42d3b8db/</link>
	<thumbnail>https://i.imgur.com/RHHyiWc.jpg</thumbnail>
</item>
<item>
	<title>Quiz Lady (2023)</title>
	<link>magnet:?xt=urn:btih:8e129fd47bc42d9f51fbb794008561b0ee6dd10f&dn=Quiz.Lady.2023.1080p.WEB.H264-AccomplishedYak[TGx]</link>
	<thumbnail>https://i.imgur.com/nYAHX4G.jpg</thumbnail>
</item>
<item>
	<title>Fingernails (2023)</title>
	<link>
	<sublink>https://rapidgator.net/file/ce53a0977496d641854913d27c1abcf5/</sublink>
	<sublink>magnet:?xt=urn:btih:501656c0900b73f03c964c1787e172ec3f8ef80a&dn=Fingernails.2023.1080p.WEB.H264-HUZZAH[TGx]</sublink>    
	</link>
	<thumbnail>https://i.imgur.com/PbnodXT.jpg</thumbnail>
</item>
<item>
	<title>Nocebo (2023)</title>
	<link>https://rapidgator.net/file/7e2ec2ef0eb44cd9d55ddb2d3a881b18/</link>
	<thumbnail>https://i.imgur.com/TnTY7WD.jpg</thumbnail>
</item>
<item>
	<title>Impuratus (2022)</title>
	<link>magnet:?xt=urn:btih:08eb0457e0bd22e01cd79455acef1129da42a9f9&dn=IMPURATUS.2023.1080p.WEBRip.DDP5.1.x265.10bit-GalaxyRG265</link>
	<thumbnail>https://i.imgur.com/KIgi2wL.jpg</thumbnail>
</item>
<item>
	<title>Butchers Crossing (2023)</title>
	<link>
	<sublink>https://rapidgator.net/file/1f3515b673837d2fbdeb5cbd08fe5dc5/</sublink>
	<sublink>magnet:?xt=urn:btih:8452344E19F3C338009541E5CEB7833487AD7DA6&dn=Butcher%27s+Crossing+%282022%29+%5B1080p%5D+%5BYTS.MX%5D</sublink>
	</link>
	<thumbnail>https://i.imgur.com/DOQyWXs.jpg</thumbnail>
</item>
<item>
	<title>Mercy Road (2023)</title>
	<link>magnet:?xt=urn:btih:4e1bdff29379e50ade19dcaf81d9693c3c09b69e&dn=Mercy.Road.2023.1090p.WEB-DL.DD+5.1.H264-BobDobbs[TGx]</link>
	<thumbnail>https://i.imgur.com/7yPJn6y.jpg</thumbnail>
</item>
<item>
	<title>Locked In (2023)</title>
	<link>
	<sublink>https://rapidgator.net/file/803459e1ba862911f6c69486bfece708/</sublink>
	<sublink>magnet:?xt=urn:btih:a88e7132a86cee3f87761595affce89ac0e3f3cf&dn=Locked.In.2023.1080p.WEB-DL.DDP5.1.Atmos.H264-AOC[TGx]</sublink>
	</link>
	<thumbnail>https://i.imgur.com/o9LN91G.jpg</thumbnail>
</item>
<item>
	<title>Gran Turismo (2023)</title>
	<link>magnet:?xt=urn:btih:6FA562A610AC13E8535A0B5D4F380CDA3513E06F&dn=Gran+Turismo+%282023%29+%5B1080p%5D+%5BYTS.MX%5D</link>
	<thumbnail>https://i.imgur.com/3KPQCaS.jpg</thumbnail>
</item>
<item>
	<title>The Last Voyage of The Demeter (2023)</title>
	<link>https://rapidgator.net/file/739b0b80a95a0d434ebd2447c33cc11d/</link>
	<thumbnail>https://i.imgur.com/a6XsFwe.jpg</thumbnail>
</item>
<item>
	<title>Retribution (2023)</title>
	<link>https://rapidgator.net/file/b21c87f0a0bd2846607abcf2e862f0e9/</link>
	<thumbnail>https://i.imgur.com/3zV4RGJ.jpg</thumbnail>
</item>
<item>
	<title>Hell House LLC Origins: The Carmichael Manor (2023)</title>
	<link>magnet:?xt=urn:btih:542D0A7004AB2F73D51DF13FA7795501168CCCAF&dn=Hell+House+LLC+Origins%3A+The+Carmichael+Manor+%282023%29+%5B1080p%5D+%5BYTS.MX%5D</link>
	<thumbnail>https://i.imgur.com/mFny0at.jpg</thumbnail>
</item>
<item>
	<title>Stalked by My Stepsister (2023)</title>
	<link>magnet:?xt=urn:btih:2E6F2E58CF5D7B493A0F182AC701894F3DFAC5A8&dn=Stalked+by+My+Stepsister+%282023%29+%5B1080p%5D+%5BYTS.MX%5D</link>
	<thumbnail>https://i.imgur.com/kDLmUyS.jpg</thumbnail>
</item>
<item>
	<title>PAW Patrol: The Mighty Movie (2023)</title>
	<link>
	<sublink>https://rapidgator.net/file/b8fe7a4954c5cb0b4cabc84c78bb311f/</sublink>
	<sublink>magnet:?xt=urn:btih:0EE26062DCCF7BE3827689E48F4904570137DBFE&dn=PAW.Patrol.The.Mighty.Movie.2023.1080p.AMZN.WEB-DL.DDP5.1.Atmos.H.264-FLUX.mkv.torrent</sublink>
	</link>
	<thumbnail>https://i.imgur.com/1AlNNoj.jpg</thumbnail>
</item>
<item>
	<title>A Bad Influence (2023)</title>
	<link>magnet:?xt=urn:btih:0ABE07D38DF8C6BF8CA8B83D6768308CCC0BFCC1&dn=A+Bad+Influence+%282023%29+%5B1080p%5D+%5BYTS.MX</link>
	<thumbnail>https://i.imgur.com/vj4Omqr.jpg</thumbnail>
</item>
<item>
	<title>A Haunting in Venice (2023)</title>
	<link>
	<sublink>https://rapidgator.net/file/e3c9715c4cd0a1d5fe1a9ea679c22251/</sublink>
	<sublink>magnet:?xt=urn:btih:2EA1973235CAF84C4C49BE1BBF8DD15F4214D3C5&dn=A+Haunting+in+Venice+%282023%29+%5B1080p%5D+%5BYTS.MX%5D</sublink>
	</link>
	<thumbnail>https://i.imgur.com/mFrdDRZ.jpg</thumbnail>
</item>
<item>
	<title>The Abode (2023)</title>
	<link>magnet:?xt=urn:btih:3A3DC072348EDDA2A30F64BA888761A37D918D38&dn=The+Abode+%282023%29+%5B1080p%5D+%5BYTS.MX%5D</link>
	<thumbnail>https://i.imgur.com/yD8fzg0.jpg</thumbnail>
</item>
<item>
	<title>His Only Son (2023)</title>
	<link>magnet:?xt=urn:btih:37b6faf5efa6502b4b639e9c9d9efb5769576dee&dn=His.Only.Son.2023.1080p.WEB-DL.DDP5.1.H264-AOC[TGx]</link>
	<thumbnail>https://i.imgur.com/H3WbdwR.jpg</thumbnail>
</item>
<item>
	<title>Mojave Diamonds (2023)</title>
	<link>magnet:?xt=urn:btih:c340596b2054ebde1221dc88bc558aef6b5d5906&dn=Mojave.Diamonds.2023.1080p.WEBRip.1400MB.DD5.1.x264-GalaxyRG</link>
	<thumbnail>https://i.imgur.com/ANdb0DF.jpg</thumbnail>
</item>
<item>
	<title>Sister Death (2023)</title>
	<link>magnet:?xt=urn:btih:8b41621a3858fc20d9b03fde7359823d36f5e9a2&dn=Sister.Death.2023.DUBBED.1080p.WEBRip.1400MB.DD5.1.x264-GalaxyRG</link>
	<thumbnail>https://i.imgur.com/UxB3VqC.jpg</thumbnail>
</item>
<item>
	<title>Lego Marvel Avengers: Code Red (2023)</title>
	<link>
	<sublink>https://rapidgator.net/file/3c5c049172e5c250d3405b5f2cbc1143/</sublink>
	<sublink>magnet:?xt=urn:btih:BCFE622864D0980D22AABCC9580995551D85D0E9&dn=Lego+Marvel+Avengers%3A+Code+Red+%282023%29+%5B1080p%5D+%5BYTS.MX%5D</sublink>
	</link>
	<thumbnail>https://i.imgur.com/oV1Vxic.jpg</thumbnail>
</item>
<item>
	<title>Pain Hustlers (2023)</title>
	<link>
	<sublink>https://rapidgator.net/file/0db94745e3f1a1e130f10dca1b5dd864/</sublink>
	<sublink>magnet:?xt=urn:btih:F1549C75FC9C73DDB234A193AE364F5264513657&dn=Pain+Hustlers+%282023%29+%5B1080p%5D+%5BYTS.MX%5D</sublink>
	</link>
	<thumbnail>https://i.imgur.com/ijMda5F.jpg</thumbnail>
</item>
<item>
	<title>Boudica (2023)</title>
	<link>
	<sublink>https://rapidgator.net/file/6e7d64534c01579e857fbfd8272ee5ac/</sublink>
	<sublink>magnet:?xt=urn:btih:0e5eda7b4c8eec98806d62c8bbed0b9b7cbdcb2d&dn=Boudica.Queen.of.War.2023.1080p.WEBRip.1400MB.DD5.1.x264-GalaxyRG</sublink>
	</link>
	<thumbnail>https://i.imgur.com/zKh26it.jpg</thumbnail>
</item>
<item>
	<title>South Park: Joining the Panderverse (2023)</title>
	<link>
	<sublink>https://rapidgator.net/file/15034f2069ef600da32ef9a6df1c16af/</sublink>
	<sublink>magnet:?xt=urn:btih:4618fb48c523655d8e1f56e71525a98dffaacb63&dn=SOUTH.PARK.JOINING.THE.PANDERVERSE.2023.1080p.WEBRip.700MB.DD5.1.x264-GalaxyRG</sublink>
	</link>	
	<thumbnail>https://i.imgur.com/s5gCBHg.jpg</thumbnail>
</item>
<item>
	<title>Suitable Flesh (2023)</title>
	<link>
	<sublink>https://rapidgator.net/file/3cc188879acf877d3aee1eb1f8f9092b/</sublink>
	<sublink>magnet:?xt=urn:btih:dafd246e892bf126a0f3f15fa3f2be61bc95929f&dn=Suitable.Flesh.2023.1080p.AMZN.WEBRip.1400MB.DD5.1.x264-GalaxyRG</sublink>
	</link>	
	<thumbnail>https://i.imgur.com/fNJMq7z.jpg</thumbnail>
</item>
<item>
	<title>Five Nights At Freddys (2023)</title>
	<link>
	<sublink>https://rapidgator.net/file/2f657cb684d5708b44954969f1f2d80c/</sublink>
	<sublink>magnet:?xt=urn:btih:6dd93fef635d66d6896f09a45a71f3e84c37223a&dn=Five.Nights.at.Freddys.2023.1080p.WEB.H264-HUZZAH[TGx]</sublink>
	</link>	
	<thumbnail>https://i.imgur.com/vcv0dj2.jpg</thumbnail>
</item>
<item>
	<title>The After (2023)</title>
	<link>https://rapidgator.net/file/0676ce7a3b5922a9d78c9a5c79a43d7f/</link>
	<thumbnail>https://i.imgur.com/r0EcsL3.jpg</thumbnail>
</item>
<item>
	<title>The Exorcist: Believer (2023)</title>
	<link>magnet:?xt=urn:btih:d4c654bf24d1b11cf874bb96ae8f0f713ece4f8b&dn=The.Exorcist.Believer.2023.1080p.WEBRip.1400MB.DD5.1.x264-GalaxyRG</link>
	<thumbnail>https://i.imgur.com/miXoy53.jpg</thumbnail>
</item>
<item>
	<title>The Royal Hotel (2023)</title>
	<link>magnet:?xt=urn:btih:fa8bda586760dfe8e59d872d4b5385a2987fe793&dn=The.Royal.Hotel.2023.1080p.AMZN.WEBRip.1400MB.DD5.1.x264-GalaxyRG</link>
	<thumbnail>https://i.imgur.com/FAAk9Pk.jpg</thumbnail>
</item>
<item>
	<title>Shrapnel (2023)</title>
	<link>magnet:?xt=urn:btih:74a7dc5bbc8b3e61381c1e7bdcb63abaf6b26df3&dn=Shrapnel.2023.1080p.WEBRip.1400MB.DD5.1.x264-GalaxyRG</link>
	<thumbnail>https://i.imgur.com/jzl3Ox1.jpg</thumbnail>
</item>
<item>
	<title>Apocalypse Clown (2023)</title>
	<link>magnet:?xt=urn:btih:6789cede0e2161ed105567972416c176aec0b4f5&dn=Apocalypse.Clown.2023.1080p.NF.WEBRip.1400MB.DD5.1.x264-GalaxyRG</link>
	<thumbnail>https://i.imgur.com/L2UU2it.jpg</thumbnail>
</item>
<item>
	<title>The Quantum Devil (2023)</title>
	<link>magnet:?xt=urn:btih:3b8a8e7ad621000011e6cd04179222b725c0711e&dn=The.Quantum.Devil.2023.1080p.WEBRip.1400MB.DD5.1.x264-GalaxyRG</link>
	<thumbnail>https://i.imgur.com/fjrmhqP.jpg</thumbnail>
</item>
<item>
	<title>If You Were the Last (2023)</title>
	<link>magnet:?xt=urn:btih:5c1e451a7d403523f3070cfe5f94dbf1c5e3f44f&dn=If.You.Were.the.Last.2023.1080p.WEBRip.1400MB.DD5.1.x264-GalaxyRG</link>
	<thumbnail>https://i.imgur.com/WISZiX5.jpg</thumbnail>
</item>
<item>
	<title>Old Dads (2023)</title>
	<link>magnet:?xt=urn:btih:e285a60f67501214a9d9aace208670ac49cb5dc3&dn=Old.Dads.2023.1080p.WEBRip.1400MB.DD5.1.x264-GalaxyRG</link>
	<thumbnail>https://i.imgur.com/KH1RLnW.jpg</thumbnail>
</item>
<item>
	<title>Saw X (2023)</title>
	<link>magnet:?xt=urn:btih:e2644e954d1c4d53341908db57dfb625d41c75c0&dn=Saw.X.2023.1080p.AMZN.WEBRip.1400MB.DD5.1.x264-GalaxyRG</link>
	<thumbnail>https://i.imgur.com/fUNY4ux.jpg</thumbnail>
</item>
<item>
	<title>Night of the Hunted (2023)</title>
	<link>magnet:?xt=urn:btih:6e214963b86590470f90f7c0dacd8a9f368e7308&dn=Night.of.the.Hunted.2023.1080p.AMZN.WEBRip.1400MB.DD5.1.x264-GalaxyRG</link>
	<thumbnail>https://i.imgur.com/GEXZ614.jpg</thumbnail>
</item>
<item>
	<title>The Other Zoey (2023)</title>
	<link>magnet:?xt=urn:btih:78fc1322f95c278b853f1980feff77ebb126b7bb&dn=The.Other.Zoey.2023.1080p.WEBRip.1400MB.DD5.1.x264-GalaxyRG</link>
	<thumbnail>https://i.imgur.com/0pWXmZj.jpg</thumbnail>
</item>
<item>
	<title>Tough Luv (2023)</title>
	<link>https://1fichier.com/?sbg2ygh7gbuaftsg8xk0</link>
	<thumbnail>https://i.imgur.com/4WcyKyU.jpg</thumbnail>
</item>
<item>
	<title>Circle City Supernatural (2023)</title>
	<link>https://1fichier.com/?lily4o002p5mb4onhbhv</link>
	<thumbnail>https://i.imgur.com/gBhanT5.jpg</thumbnail>
</item>
<item>
	<title>Birthright Outlaw (2023)</title>
	<link>https://1fichier.com/?jlgbzau2e3b7cdkjl6d9</link>
	<thumbnail>https://i.imgur.com/uTEHhm4.jpg</thumbnail>
</item>
<item>
	<title>Outpost (2022)</title>
	<link>https://1fichier.com/?c9cqamzh6r5web6nku6t</link>
	<thumbnail>https://i.imgur.com/4nCfRAx.jpg</thumbnail>
</item>
<item>
	<title>Dark Harvest (2023)</title>
	<link>https://1fichier.com/?qclcqtr5y656jqhzw138</link>
	<thumbnail>https://i.imgur.com/xRRWdbK.jpg</thumbnail>
</item>
<item>
	<title>Ballerina (2023)</title>
	<link>https://1fichier.com/?lpiaczu5v33ow0uefawe</link>
	<thumbnail>https://i.imgur.com/SpI5dcq.jpg</thumbnail>
</item>
<item>
	<title>Mia and the Dragon Princess (2023)</title>
	<link>https://1fichier.com/?f64qpu6x6jdmo860t6ki</link>
	<thumbnail>https://i.imgur.com/ARm2MBF.jpg</thumbnail>
</item>
<item>
	<title>They Wait in the Dark (2022)</title>
	<link>https://1fichier.com/?7pk929uddnltbkjfru3z</link>
	<thumbnail>https://i.imgur.com/qs4jcKq.jpg</thumbnail>
</item>
<item>
	<title>Dear David (2023)</title>
	<link>https://1fichier.com/?jqbfenkhl1hahkd77hs1</link>
	<thumbnail>https://i.imgur.com/SDOOvQu.jpg</thumbnail>
</item>
<item>
	<title>15 Cameras (2023)</title>
	<link>https://1fichier.com/?jsa5ctjww9ly9an6kny8</link>
	<thumbnail>https://i.imgur.com/fhkIsIZ.jpg</thumbnail>
</item>
<item>
	<title>Herd (2023)</title>
	<link>https://1fichier.com/?4whpg5f17y5ljw8tu4i8</link>
	<thumbnail>https://i.imgur.com/gyqNrkU.jpg</thumbnail>
</item>
<item>
	<title>The Bell Keeper (2023)</title>
	<link>https://1fichier.com/?pn83am4nzwgcwqnc65yr</link>
	<thumbnail>https://i.imgur.com/v1B0UPn.jpg</thumbnail>
</item>
<item>
	<title>Scarygirl (2023)</title>
	<link>https://1fichier.com/?7lwjudizeezwjokzp3bk</link>
	<thumbnail>https://i.imgur.com/OxWMlPI.jpg</thumbnail>
</item>
<item>
	<title>In the Fire (2023)</title>
	<link>https://1fichier.com/?0zx0ctvhbdepydowucae</link>
	<thumbnail>https://i.imgur.com/OxobEby.jpg</thumbnail>
</item>
<item>
	<title>Mortal Kombat Legends: Cage Match (2023)</title>
	<link>https://1fichier.com/?cwhmfiqn3bxze96hevhf</link>
	<thumbnail>https://i.imgur.com/WrUa5ed.jpg</thumbnail>
</item>
<item>
	<title>The Puppetman (2023)</title>
	<link>https://1fichier.com/?1kck3hxw4qzxodgs3ns7</link>
	<thumbnail>https://i.imgur.com/LOo7t9H.jpg</thumbnail>
</item>
<item>
	<title>The Burial (2023)</title>
	<link>https://1fichier.com/?jv1fe13fe25fjf3dja0d</link>
	<thumbnail>https://i.imgur.com/7lNEKsZ.jpg</thumbnail>
</item>
<item>
	<title>Expend4bles (2023)</title>
	<link>https://1fichier.com/?j4e7unn6f71ttcvfeyi7</link>
	<thumbnail>https://i.imgur.com/J0HgioJ.jpg</thumbnail>
</item>
<item>
	<title>The Miracle Club (2023)</title>
	<link>https://1fichier.com/?2xyc9yg4g0z3xw2msnf1</link>
	<thumbnail>https://i.imgur.com/FyIoSZn.jpg</thumbnail>
</item>
<item>
	<title>It Lives Inside (2023)</title>
	<link>https://1fichier.com/?5ax13uy35vpw6i4o4chi</link>
	<thumbnail>https://i.imgur.com/lMDRg7T.jpg</thumbnail>
</item>
<item>
	<title>Down Low (2023)</title>
	<link>https://1fichier.com/?c68wvrcadwe11pwv5mcm</link>
	<thumbnail>https://i.imgur.com/gbCFGs5.jpg</thumbnail>
</item>
<item>
	<title>Mission: Impossible - Dead Reckoning Part One (2023)</title>
	<link>https://1fichier.com/?6jzmsmzru7yqv0jdnmk4</link>
	<thumbnail>https://i.imgur.com/k1gWnU8.jpg</thumbnail>
</item>
<item>
	<title>The Mill (2023)</title>
	<link>https://1fichier.com/?d0wv5eyj0drocodwagqf</link>
	<thumbnail>https://i.imgur.com/MULzvQf.jpg</thumbnail>
</item>
<item>
	<title>Megalodon: The Frenzy (2023)</title>
	<link>https://1fichier.com/?2nmis2y3dq8j2g0by641</link>
	<thumbnail>https://i.imgur.com/ZPUqFlL.jpg</thumbnail>
</item>
<item>
	<title>Vindicta (2023)</title>
	<link>https://1fichier.com/?gu9ji5zwzek6xdq39n7e</link>
	<thumbnail>https://i.imgur.com/3TTglAP.jpg</thumbnail>
</item>
<item>
	<title>Monsters of California (2023)</title>
	<link>https://1fichier.com/?xs2q1cz91agoszf36du8</link>
	<thumbnail>https://i.imgur.com/I6c5bZP.jpg</thumbnail>
</item>
<item>
	<title>Borderline (2023)</title>
	<link>https://1fichier.com/?rxy2h8e60jvaxkc3vs9x</link>
	<thumbnail>https://i.imgur.com/vmW1YjF.jpg</thumbnail>
</item>
<item>
	<title>The Kill Room (2023)</title>
	<link>https://1fichier.com/?bytkqaz1zh8cnhuf0spi</link>
	<thumbnail>https://i.imgur.com/1hPGAl8.jpg</thumbnail>
</item>
<item>
	<title>Desperation Road (2023)</title>
	<link>https://1fichier.com/?3ydvwzagys8xgazrx8fc</link>
	<thumbnail>https://i.imgur.com/IkLoeRI.jpg</thumbnail>
</item>
<item>
	<title>Fair Play (2023)</title>
	<link>https://1fichier.com/?42rw61jmpeqeikaz5j7i</link>
	<thumbnail>https://i.imgur.com/r4J8btH.jpg</thumbnail>
</item>
<item>
	<title>V/H/S/85 (2023)</title>
	<link>https://1fichier.com/?it4xtduxdzofqbwk1q4u</link>
	<thumbnail>https://i.imgur.com/Ln32Dc6.jpg</thumbnail>
</item>
<item>
	<title>The Caine Mutiny Court-Martial (2023)</title>
	<link>https://1fichier.com/?8ezuxdk5rvv2ssuv1nad</link>
	<thumbnail>https://i.imgur.com/90DPi21.jpg</thumbnail>
</item>
<item>
	<title>Pet Sematary: Bloodlines (2023)</title>
	<link>https://1fichier.com/?0cu6t0if5vugxd2xtg31</link>
	<thumbnail>https://i.imgur.com/JDvuUJI.jpg</thumbnail>
</item>
<item>
	<title>Totally Killer (2023)</title>
	<link>https://1fichier.com/?xv2euxnc0tmz1qnh27sc</link>
	<thumbnail>https://i.imgur.com/NNc0PCN.jpg</thumbnail>
</item>
<item>
	<title>Passages (2023)</title>
	<link>https://1fichier.com/?cm5ft56189j21bywmwqj</link>
	<thumbnail>https://i.imgur.com/YPaKFpI.jpg</thumbnail>
</item>
<item>
	<title>Don't Look Away (2023)</title>
	<link>https://1fichier.com/?89r47ymqlhfm6eyguldq</link>
	<thumbnail>https://i.imgur.com/Wkv2lcY.jpg</thumbnail>
</item>
<item>
	<title>The Mean One (2022)</title>
	<link>https://1fichier.com/?dm1sxi3oslhpt0rovidy</link>
	<thumbnail>https://i.imgur.com/oU53QHo.jpg</thumbnail>
</item>
<item>
	<title>Monster High 2 (2023)</title>
	<link>https://1fichier.com/?g7d5zr1hnftw1z76xp64</link>
	<thumbnail>https://i.imgur.com/h0EPiXp.jpg</thumbnail>
</item>
<item>
	<title>Dreamin' Wild (2023)</title>
	<link>https://1fichier.com/?w8k0ct2to3w0pzyqq2m3</link>
	<thumbnail>https://i.imgur.com/3by8x93.jpg</thumbnail>
</item>
<item>
	<title>Headspace (2023)</title>
	<link>https://1fichier.com/?dtyatxrgpo55gymcd39r</link>
	<thumbnail>https://i.imgur.com/zzkANcv.jpg</thumbnail>
</item>
<item>
	<title>Haunted Mansion (2023)</title>
	<link>https://1fichier.com/?fpf064nk7yw8aschmor6</link>
	<thumbnail>https://i.imgur.com/jZCjc1d.jpg</thumbnail>
</item>
<item>
	<title>After Everything (2023)</title>
	<link>https://1fichier.com/?bo3rk25o2twiyz16zstk</link>
	<thumbnail>https://i.imgur.com/bZzIQdb.jpg</thumbnail>
</item>
<item>
	<title>The Nun II (2023)</title>
	<link>https://1fichier.com/?3ryorxb4dckwv94dj5fh</link>
	<thumbnail>https://i.imgur.com/kv7tuMs.jpg</thumbnail>
</item>
<item>
	<title>The Equalizer 3 (2023)</title>
	<link>https://1fichier.com/?7jmb9rbzww5opggul05u</link>
	<thumbnail>https://i.imgur.com/eBceICY.jpg</thumbnail>
</item>
<item>
	<title>Kindling (2023)</title>
	<link>https://1fichier.com/?bltx80qewp5my64sckuf</link>
	<thumbnail>https://i.imgur.com/1W2SIn9.jpg</thumbnail>
</item>
<item>
	<title>The Re-Education of Molly Singer (2023)</title>
	<link>https://1fichier.com/?xe9os191qibi2pyckpva</link>
	<thumbnail>https://i.imgur.com/275zbPz.jpg</thumbnail>
</item>
<item>
	<title>Sound of Freedom (2022)</title>
	<link>https://1fichier.com/?726xhtnjgwhu97pgbc52</link>
	<thumbnail>https://i.imgur.com/X9GUW6Z.jpg</thumbnail>
</item>
<item>
	<title>1943 (2023)</title>
	<link>https://1fichier.com/?6yclzuu0uj5z3suyjiyf</link>
	<thumbnail>https://i.imgur.com/rbMd4nt.jpg</thumbnail>
</item>
<item>
	<title>Deliver Us (2023)</title>
	<link>https://1fichier.com/?7q7pf01fjwfzry8hk3nl</link>
	<thumbnail>https://i.imgur.com/3dXufTL.jpg</thumbnail>
</item>
<item>
	<title>Appendage (2023)</title>
	<link>https://1fichier.com/?2zkrv6y4lzbtjyw4wa4q</link>
	<thumbnail>https://i.imgur.com/iuNcO7v.jpg</thumbnail>
</item>
<item>
	<title>Beaten to Death (2023)</title>
	<link>https://1fichier.com/?r0704ry2mltdp4sh29bf</link>
	<thumbnail>https://i.imgur.com/wvoq9TQ.jpg</thumbnail>
</item>
<item>
	<title>Muzzle (2023)</title>
	<link>https://1fichier.com/?p3ji012oqcgbmapzlmqu</link>
	<thumbnail>https://i.imgur.com/Zyj5b1N.jpg</thumbnail>
</item>
<item>
	<title>The Exorcists (2023)</title>
	<link>https://1fichier.com/?x3mhi0jo84ib4q8j6mvf</link>
	<thumbnail>https://i.imgur.com/lXwsOow.jpg</thumbnail>
</item>
<item>
	<title>57 Seconds (2023)</title>
	<link>https://1fichier.com/?8drnswcvbp78f6i0mw9q</link>
	<thumbnail>https://i.imgur.com/JLxM1hc.jpg</thumbnail>
</item>
<item>
	<title>M.I. - Dead Reckoning Part One (2023) (HC Subs)</title>
	<link>https://1fichier.com/?i599odxi3vvj6slbipgz</link>
	<thumbnail>https://i.imgur.com/k1gWnU8.jpg</thumbnail>
</item>
<item>
	<title>Reptile (2023)</title>
	<link>https://1fichier.com/?ff1jansj4hhr41ck1al5</link>
	<thumbnail>https://i.imgur.com/ZwGCu4b.jpg</thumbnail>
</item>
<item>
	<title>Flora and Son (2023)</title>
	<link>https://1fichier.com/?hp6dnsega3l8nnbze825</link>
	<thumbnail>https://i.imgur.com/LJJjBPW.jpg</thumbnail>
</item>
<item>
	<title>Heist 88 (2023)</title>
	<link>https://1fichier.com/?hucb84ep3iwt6tqbxvc7</link>
	<thumbnail>https://i.imgur.com/w2e22wG.jpg</thumbnail>
</item>
<item>
	<title>Barber (2023)</title>
	<link>https://1fichier.com/?bswebz57qe9p0uuk11qx</link>
	<thumbnail>https://i.imgur.com/sHUYCH6.jpg</thumbnail>
</item>
<item>
	<title>The Wonderful Story of Henry Sugar (2023)</title>
	<link>https://1fichier.com/?swrxr4f0vp7955t86ik7</link>
	<thumbnail>https://i.imgur.com/pvi6MHr.jpg</thumbnail>
</item>
<item>
	<title>My Big Fat Greek Wedding 3 (2023)</title>
	<link>https://1fichier.com/?xk8l6lz7wy5macbpal87</link>
	<thumbnail>https://i.imgur.com/X2dp8Yg.jpg</thumbnail>
</item>
<item>
	<title>Gran Turismo (2023)</title>
	<link>https://1fichier.com/?ema3reu4toh54dfwgf0l</link>
	<thumbnail>https://i.imgur.com/HZ8anav.jpg</thumbnail>
</item>
<item>
	<title>All Fun and Games (2023)</title>
	<link>https://1fichier.com/?ph63vkt0tzrse70pjbm2</link>
	<thumbnail>https://i.imgur.com/Iu8cRiF.jpg</thumbnail>
</item>
<item>
	<title>Scooby-Doo! and Krypto, Too! (2023)</title>
	<link>https://1fichier.com/?ju6c9tmxv8v0yuaqi99j</link>
	<thumbnail>https://i.imgur.com/4Ve5xZI.jpg</thumbnail>
</item>
<item>
	<title>Moon Students (2023)</title>
	<link>https://1fichier.com/?3gjwximm06ueae4qybvx</link>
	<thumbnail>https://i.imgur.com/z097sFZ.jpg</thumbnail>
</item>
<item>
	<title>Dark Asset (2023)</title>
	<link>https://1fichier.com/?vizf12q9gc2ew5sridy7</link>
	<thumbnail>https://i.imgur.com/q0fYOjo.jpg</thumbnail>
</item>
<item>
	<title>Slotherhouse (2023)</title>
	<link>https://1fichier.com/?ya6ig0plnb4j4m4unrf6</link>
	<thumbnail>https://i.imgur.com/LHmqcbA.jpg</thumbnail>
</item>
<item>
	<title>The Hill (2023)</title>
	<link>https://1fichier.com/?z93epea8c2q9gnsomyow</link>
	<thumbnail>https://i.imgur.com/msntqEF.jpg</thumbnail>
</item>
<item>
	<title>The Retirement Plan (2023)</title>
	<link>https://1fichier.com/?kae45nesm7or7e4fujmn</link>
	<thumbnail>https://i.imgur.com/Ry5avpH.jpg</thumbnail>
</item>
<item>
	<title>The Haunting of Hell Hole Mine (2023)</title>
	<link>https://1fichier.com/?zfdu96n2ge0f7id1tbei</link>
	<thumbnail>https://i.imgur.com/1xSGCbG.jpg</thumbnail>
</item>
<item>
	<title>Spy Kids: Armageddon (2023)</title>
	<link>https://1fichier.com/?ifl8fhsv6zwjqmtdbzyy</link>
	<thumbnail>https://i.imgur.com/PVxjlJa.jpg</thumbnail>
</item>
<item>
	<title>No One Will Save You (2023)</title>
	<link>https://1fichier.com/?lcq159gkd6637kywwai3</link>
	<thumbnail>https://i.imgur.com/niG3XlJ.jpg</thumbnail>
</item>
<item>
	<title>Bottoms (2023)</title>
	<link>https://1fichier.com/?ke0i4k1mtu7w1yulffx5</link>
	<thumbnail>https://i.imgur.com/g2ZVJlX.jpg</thumbnail>
</item>
<item>
	<title>A New Breed of Criminal (2023)</title>
	<link>https://1fichier.com/?chtig2dstzjop2f260fp</link>
	<thumbnail>https://i.imgur.com/8auuR4y.jpg</thumbnail>
</item>
<item>
	<title>The Good Mother (2023)</title>
	<link>https://1fichier.com/?04znomvwot13ldmz9xiy</link>
	<thumbnail>https://i.imgur.com/Q3QUhRD.jpg</thumbnail>
</item>
item>
	<title>Cassandro (2023)</title>
	<link>
		<sublink>https://hexupload.net/td8ho1td7r54</sublink>
		<sublink>https://streamtape.com/v/wr96KV4RLbcJ7Pv/</sublink>
		<sublink>https://hexupload.net/8nzm3nz89iz4</sublink>
	</link>
	<thumbnail>https://i.imgur.com/28bD7NV.jpg</thumbnail>
</item>
item>
	<title>Til Death Do Us Part (2023)</title>
	<link>
		<sublink>https://hexupload.net/pagk3g508eom</sublink>
		<sublink>https://streamtape.com/v/drObMl3x2xT7oG/</sublink>
		<sublink>https://hexupload.net/hj1z079dflr4</sublink>
	</link>
	<thumbnail>https://i.imgur.com/R8xceIQ.jpg</thumbnail>
</item>
item>
	<title>Nandor Fodor and the Talking Mongoose (2023)</title>
	<link>
		<sublink>https://hexupload.net/7a1krugn1l4f</sublink>
		<sublink>https://streamtape.com/v/xyy10KdQ87Uka8q/</sublink>
		<sublink>https://hexupload.net/frdte1cnk45k</sublink>
	</link>
	<thumbnail>https://i.imgur.com/eJYu11g.jpg</thumbnail>
</item>
item>
	<title>Golda (2023)</title>
	<link>
		<sublink>https://hexupload.net/f6xqzzsuad3h</sublink>
		<sublink>https://streamtape.com/v/WoR3P4o4arFqk1/</sublink>
		<sublink>https://hexupload.net/4m6ud5xp49v4</sublink>
	</link>
	<thumbnail>https://i.imgur.com/zQyMUQQ.jpg</thumbnail>
</item>
item>
	<title>American Outlaws (2023)</title>
	<link>
		<sublink>https://hexupload.net/63kq27h4hsme</sublink>
		<sublink>https://streamtape.com/v/OgwLPLkZ0liZ34M/</sublink>
		<sublink>https://hexupload.net/j5mxuqe7ypz8</sublink>
		<sublink>https://hexupload.net/b2dqdv6xk7p2</sublink>
	</link>
	<thumbnail>https://i.imgur.com/EkG0N6w.jpg</thumbnail>
</item>
item>
	<title>The Haunting at Saint Joseph (2023)</title>
	<link>
		<sublink>https://hexupload.net/y5kwqcb1ssde</sublink>
		<sublink>https://streamtape.com/v/zGwyzgKpeYsYzyB/</sublink>
		<sublink>https://hexupload.net/j79r9110ynja</sublink>
	</link>
	<thumbnail>https://i.imgur.com/VpIOL8z.jpg</thumbnail>
</item>
item>
	<title>Superpower (2023)</title>
	<link>
		<sublink>https://hexupload.net/wmp0fbxg4l7h</sublink>
	</link>
	<thumbnail>https://i.imgur.com/GZ94eGv.jpg</thumbnail>
</item>
item>
	<title>Blue Beetle (2023)</title>
	<link>
		<sublink>https://hexupload.net/wzslp5szfak5</sublink>
		<sublink>https://streamtape.com/v/G317y419AvSmg3/</sublink>
		<sublink>https://hexupload.net/2hkd2g8hu7g5</sublink>
		<sublink>https://hexupload.net/rh4kdv7kwgzw</sublink>
	</link>
	<thumbnail>https://i.imgur.com/zWAKk7P.jpg</thumbnail>
</item>
