<?xml version="1.0" encoding="UTF-8"?>
<?xml-stylesheet href="hide-it.xsl" type="text/xsl"?>
<item>
	<title>Hanky Panky (2023)</title>
	<link>
	        <sublink>magnet:?xt=urn:btih:09bb4446ab8d0b99184753264050e480e92d4dd1&dn=Hanky.Panky.2024.1080p.WEBRip.1400MB.DD5.1.x264-GalaxyRG</sublink>
	</link>
	<thumbnail>https://i.imgur.com/BTVpR37.jpeg</thumbnail>
</item>
<item>
	<title>Accidental Texan (2023)</title>
	<link>
	        <sublink>magnet:?xt=urn:btih:549C816D3B77BCEC09E46A3EAB5A15EF33B43A32&dn=Accidental+Texan+%282023%29+%5B1080p%5D+%5BYTS.MX%5D</sublink>
	</link>
	<thumbnail>https://i.imgur.com/9wu9DCD.jpeg</thumbnail>
</item>
<item>
	<title>MR-9 Do Or Die (2023)</title>
	<link>
	        <sublink>magnet:?xt=urn:btih:5CC45A293F1CE044D413B208531EF9EB7D337D37&dn=MR-9%3A+Do+or+Die+%282023%29+%5B1080p%5D+%5BYTS.MX%5D</sublink>
	</link>
	<thumbnail>https://i.imgur.com/FcTNaPb.jpeg</thumbnail>
</item>
<item>
	<title>Justice League Crisis On Infinite Earths: Part Two (2024)</title>
	<link>
	        <sublink>https://rapidgator.net/file/b6e1249314f6682c4eafd1fa16901885/</sublink>
	</link>
	<thumbnail>https://i.imgur.com/ypSeGdr.jpeg</thumbnail>
</item>
<item>
	<title>Downtown Owl (2023)</title>
	<link>
	        <sublink>magnet:?xt=urn:btih:9983644ce1422c0ef7167d597e9d7501944515eb&dn=Downtown.Owl.2023.1080p.WEBRip.1400MB.DD5.1.x264-GalaxyRG</sublink>
	</link>
	<thumbnail>https://i.imgur.com/9rGhnjH.jpeg</thumbnail>
</item>
<item>
	<title>Arthur The King (2024)</title>
	<link>
	        <sublink>magnet:?xt=urn:btih:f2f90f959e4ece8c69a1b9a42b7b3bb2b88f0095&dn=Arthur.the.King.2024.1080p.AMZN.WEBRip.DDP5.1.x265.10bit-GalaxyRG265</sublink>
	</link>
	<thumbnail>https://i.imgur.com/cK7AGkL.jpeg</thumbnail>
</item>
<item>
	<title>Monkey Man (2024)</title>
	<link>
	        <sublink>magnet:?xt=urn:btih:4909fddb7b0bcda979f459e80207019a7c2bbcd9&dn=Monkey.Man.2024.1080p.AMZN.WEBRip.DDP5.1.x265.10bit-GalaxyRG265</sublink>
	</link>
	<thumbnail>https://i.imgur.com/iwWoDXZ.jpeg</thumbnail>
</item>
<item>
	<title>Blood For Dust (2023)</title>
	<link>
	        <sublink>magnet:?xt=urn:btih:687f531d9d932a898edee2c49453a2f72e2c6f35&dn=Blood.For.Dust.2023.1080p.AMZN.WEBRip.DDP5.1.x265.10bit-GalaxyRG265</sublink>
	</link>
	<thumbnail>https://i.imgur.com/gLYuSGq.jpeg</thumbnail>
</item>
<item>
	<title>Rebel Moon Part Two: The Scargiver (2024)</title>
	<link>
	        <sublink>magnet:?xt=urn:btih:1faf79f8555981e0c836bb5b8d189a354fde749f&dn=Rebel.Moon.Part.Two.The.Scargiver.2024.1080p.NF.WEBRip.DDP5.1.x265.10bit-GalaxyRG265</sublink>
	</link>
	<thumbnail>https://i.imgur.com/oaupX0A.jpeg</thumbnail>
</item>
<item>
	<title>Asphalt City (2024)</title>
	<link>
	        <sublink>magnet:?xt=urn:btih:e4af529df584c9a552fb24bd2c87e0ba8436b9e0&dn=Asphalt.City.2023.1080p.AMZN.WEBRip.DDP5.1.x265.10bit-GalaxyRG265</sublink>
	</link>
	<thumbnail>https://i.imgur.com/OSDmsps.jpeg</thumbnail>
</item>
<item>
	<title>Problemista (2023)</title>
	<link>
	        <sublink>magnet:?xt=urn:btih:b0a9f5fbe9041932c5764f3f2533c56acb2e2889&dn=Problemista.2023.1080p.AMZN.WEBRip.DDP5.1.x265.10bit-GalaxyRG265</sublink>
	</link>
	<thumbnail>https://i.imgur.com/3bLzt21.jpeg</thumbnail>
</item>
<item>
	<title>Late Night with the Devil (2023)</title>
	<link>
	        <sublink>magnet:?xt=urn:btih:5dca27e218f4d19342616dd1b92df6e7e0f28404&dn=Late.Night.with.the.Devil.2023.1080p.AMZN.WEBRip.DDP5.1.x265.10bit-GalaxyRG265</sublink>
	</link>
	<thumbnail>https://i.imgur.com/u2RE03x.jpeg</thumbnail>
</item>
<item>
	<title>Bad Hombres (2024)</title>
	<link>
	        <sublink>https://rapidgator.net/file/3b07df2dd7e8997f7ebdb981450b53d2/</sublink>
	</link>
	<thumbnail>https://i.imgur.com/XsPAyYu.jpeg</thumbnail>
</item>
<item>
	<title>Sweet Dreams (2024)</title>
	<link>
		<sublink>magnet:?xt=urn:btih:513380ddfe4f8e67571901934d198bc799f4ae9e&dn=Sweet.Dreams.2024.1080p.AMZN.WEBRip.DDP5.1.x265.10bit-GalaxyRG265</sublink>
	</link>
	<thumbnail>https://i.imgur.com/iZf3KGx.jpeg</thumbnail>
</item>
<item>
	<title>Immaculate (2024)</title>
	<link>
		<sublink>magnet:?xt=urn:btih:e30231ab5aa8f7c563c94bad8de7e91b3e19d2f1&dn=Immaculate.2024.1080p.AMZN.WEBRip.DDP5.1.x265.10bit-GalaxyRG265</sublink>
	</link>
	<thumbnail>https://i.imgur.com/B0Ehjlb.jpeg</thumbnail>
</item>
<item>
	<title>Dune Part Two (2024)</title>
	<link>
	   <sublink>magnet:?xt=urn:btih:b1caf2a9c5cabc705b056c06dc5365f1eaf4c098&dn=Dune.Part.Two.2024.1080p.WEBRip.1600MB.DD2.0.x264-GalaxyRG</sublink>
	</link>
	<thumbnail>https://i.imgur.com/4QKnZ1Q.jpeg</thumbnail>
</item>
<item>
	<title>Hundreds Of Beavers (2024)</title>
	<link>
	        <sublink>https://rapidgator.net/file/9c4355f3639d197e58bacd8efcac9749</sublink>
	</link>
	<thumbnail>https://i.imgur.com/EjAJD8r.jpeg</thumbnail>
</item>
<item>
	<title>Model House (2024)</title>
	<link>
	        <sublink>magnet:?xt=urn:btih:8bf1643eb92c7b00e94e72ae41f902de36101e26&dn=Model.House.2024.1080p.WEBRip.DDP5.1.x265.10bit-GalaxyRG265</sublink>
	</link>
	<thumbnail>https://i.imgur.com/Xq3eZro.jpeg</thumbnail>
</item>
<item>
	<title>Pure O (2023)</title>
	<link>
	        <sublink>magnet:?xt=urn:btih:d9de93d4ceebdb9d6d62c3c3da790fb25b29602f&dn=Pure.O.2023.1080p.AMZN.WEBRip.DDP5.1.x265.10bit-GalaxyRG265</sublink>
	</link>
	<thumbnail>https://i.imgur.com/2V5SFQy.jpeg</thumbnail>
</item>
<item>
	<title>Riddle of Fire (2023)</title>
	<link>
		<sublink>magnet:?xt=urn:btih:bdf6e245606070e740e81f7c8ed683852c1dbc95&dn=Riddle.of.Fire.2023.1080p.AMZN.WEBRip.DDP5.1.x265.10bit-GalaxyRG265</sublink>
	</link>
	<thumbnail>https://i.imgur.com/Tn2KUZF.jpeg</thumbnail>
</item>
<item>
	<title>LaRoy Texas (2024)</title>
	<link>
		<sublink>magnet:?xt=urn:btih:718b6e6e9630ed15dc04f3bace7ea32b1f4f9126&dn=LaRoy.Texas.2023.1080p.AMZN.WEBRip.DDP5.1.x265.10bit-GalaxyRG265</sublink>
	</link>
	<thumbnail>https://i.imgur.com/2CzdUyH.jpeg</thumbnail>
</item>
<item>
	<title>Woody Woodpecker: Goes To Camp (2023)</title>
	<link>
		<sublink>magnet:?xt=urn:btih:0d44f413bb682351cc173f884b09ae03f798857f&dn=Woody.Woodpecker.Goes.to.Camp.2024.1080p.NF.WEBRip.1400MB.DD5.1.x264-GalaxyRG</sublink>
	</link>
	<thumbnail>https://i.imgur.com/ALOBbmh.jpeg</thumbnail>
</item>
<item>
	<title>Parachute (2023)</title>
	<link>
		<sublink>magnet:?xt=urn:btih:a8ddcb67424d71e2ba21f5f8d763315809a4619f&dn=Parachute.2023.1080p.WEBRip.1400MB.DD5.1.x264-GalaxyRG</sublink>
	</link>
	<thumbnail>https://i.imgur.com/HZZR1RO.jpeg</thumbnail>
</item>
<item>
	<title>Damaged (2024)</title>
	<link>
		<sublink>magnet:?xt=urn:btih:6b803f602e929f06e26582d96619498c1227c5c5&dn=Damaged.2024.1080p.AMZN.WEBRip.DDP5.1.x265.10bit-GalaxyRG265</sublink>
	</link>
	<thumbnail>https://i.imgur.com/DZgbGS6.jpeg</thumbnail>
</item>
<item>
	<title>The Greatest Hits (2024)</title>
	<link>
		<sublink>magnet:?xt=urn:btih:1c062e877cf64b86634a89ab1bb063d3c21eb314&dn=The.Greatest.Hits.2024.1080p.DSNP.WEBRip.DDP5.1.x265.10bit-GalaxyRG265</sublink>
	</link>
	<thumbnail>https://i.imgur.com/s3LTUv0.jpeg</thumbnail>
</item>
<item>
	<title>Sleeping Dogs (2024)</title>
	<link>
		<sublink>magnet:?xt=urn:btih:c985db4675980682257b2f9a146bb3aa00c3de0e&dn=Sleeping.Dogs.2024.1080p.AMZN.WEBRip.DDP5.1.x265.10bit-GalaxyRG265</sublink>
	</link>
	<thumbnail>https://i.imgur.com/VqewS29.jpeg</thumbnail>
</item>
<item>
	<title>Kung Fu Panda 4 (2024)</title>
	<link>
		<sublink>magnet:?xt=urn:btih:40d7d1a61ad8978e0322c96709de6d5f0afc31db&dn=Kung.Fu.Panda.4.2024.1080p.AMZN.WEBRip.DDP5.1.x265.10bit-GalaxyRG265</sublink>
	</link>
	<thumbnail>https://i.imgur.com/dSBsMC2.jpeg</thumbnail>
</item>
<item>
	<title>Wicked Little Letters (2023)</title>
	<link>
		<sublink>magnet:?xt=urn:btih:414417afa26699c8f892d6f525514625a9761593&dn=Wicked.Little.Letters.2023.1080p.WEBRip.1400MB.DD5.1.x264-GalaxyRG</sublink>
	</link>
	<thumbnail>https://i.imgur.com/hulK0qK.jpeg</thumbnail>
</item>
<item>
	<title>Seagrass (2023)</title>
	<link>
		<sublink>magnet:?xt=urn:btih:1c292870980483b7b39431467b4cbc430e7dbfcd&dn=Seagrass.2023.1080p.AMZN.WEBRip.DDP5.1.x265.10bit-GalaxyRG265</sublink>
	</link>
	<thumbnail>https://i.imgur.com/I9dRCj5.jpeg</thumbnail>
</item>
<item>
	<title>Scoop (2024)</title>
	<link>
		<sublink>magnet:?xt=urn:btih:2316368e879d76684f6644aa5380d3275b62afff&dn=Scoop.2024.1080p.NF.WEBRip.DDP5.1.x265.10bit-GalaxyRG265</sublink>
	</link>
	<thumbnail>https://i.imgur.com/u7j6hFq.jpeg</thumbnail>
</item>
<item>
	<title>Knox Goes Away (2023)</title>
	<link>
		<sublink>magnet:?xt=urn:btih:aefbad76430e8a4f00a120f8edd72168bf14493c&dn=Knox.Goes.Away.2023.1080p.AMZN.WEBRip.DDP5.1.x265.10bit-GalaxyRG265</sublink>
	</link>
	<thumbnail>https://i.imgur.com/lXyYSVV.jpeg</thumbnail>
</item>
<item>
	<title>Strictly Confidential (2024)</title>
	<link>
		<sublink>magnet:?xt=urn:btih:324c3481b1cfa641a64f47befbfb0bf73aec63bc&dn=Strictly.Confidential.2024.1080p.AMZN.WEBRip.DDP5.1.x265.10bit-GalaxyRG265</sublink>
	</link>
	<thumbnail>https://i.imgur.com/LWUddmp.jpeg</thumbnail>
</item>
<item>
	<title>Baghead (2023)</title>
	<link>
		<sublink>magnet:?xt=urn:btih:f4803d48cb5eb1f5efdd4ca15a406545cf018b58&dn=Baghead.2023.1080p.WEBRip.DDP5.1.x265.10bit-GalaxyRG265</sublink>
	</link>
	<thumbnail>https://i.imgur.com/WZ15Q2t.jpeg</thumbnail>
</item>
<item>
	<title>How to Date Billy Walsh (2024)</title>
	<link>
		<sublink>magnet:?xt=urn:btih:ad707c10d012dd488a8e479cd2bda069ffed827e&dn=How.to.Date.Billy.Walsh.2024.1080p.AMZN.WEBRip.1400MB.DD5.1.x264-GalaxyRG</sublink>
	</link>
	<thumbnail>https://i.imgur.com/MtvpaLk.jpeg</thumbnail>
</item>
<item>
	<title>Musica (2024)</title>
	<link>
		<sublink>magnet:?xt=urn:btih:981ccb8ed47631e39e003b6f9025640e80c25dd4&dn=Musica.2024.1080p.AMZN.WEBRip.DDP5.1.x265.10bit-GalaxyRG265</sublink>
	</link>
	<thumbnail>https://i.imgur.com/WCLUlnZ.jpeg</thumbnail>
</item>
<item>
	<title>Monster Mash (2024)</title>
	<link>
	        <sublink>magnet:?xt=urn:btih:1127c54518f3dfe4d33c0fbd8fd104719ce8f9a8&dn=Monster.Mash.2024.1080p.WEBRip.DDP2.0.x265.10bit-GalaxyRG265</sublink>
	</link>
	<thumbnail>https://i.imgur.com/e6xb8Kt.jpeg</thumbnail>
</item>
