{
  "items": [
    {
      "type": "dir",
      "title": "[COLORwhite]New Movies[/COLOR]",
      "link": "https://mfirepo.github.io/hal/newrels.json"
    },
    {
      "type": "dir",
      "title": "[COLORwhite]4K Movies[/COLOR]",
      "link": "https://mfirepo.github.io/hal/4k.json"
    },
    {
      "type": "dir",
      "title": "[COLORwhite]British Cinema[/COLOR]",
      "link": "https://mfirepo.github.io/hal/brit.json"
    },
    {
      "type": "dir",
      "title": "[COLORwhite]TV Shows[/COLOR]",
      "link": "https://www.themoviedb.org/list/8237878"
    },
    {
      "type": "dir",
      "title": "[COLORwhite]New Documentaries[/COLOR]",
      "link": "https://mfirepo.github.io/hal/docu.json"
    },
    {
      "type": "dir",
      "title": "[COLORwhite]Documentary Channels[/COLOR]",
      "link": "https://mfirepo.github.io/hal/livedocs.json"
    },
    {
      "type": "dir",
      "title": "[COLORwhite]UK Channels[/COLOR]",
      "link": "plugin://plugin.video.samm_tv/samsung_tv/region/gb"
    },
    {
      "type": "dir",
      "title": "[COLORwhite]US Channels[/COLOR]",
      "link": "plugin://plugin.video.samm_tv/samsung_tv/region/us"
    },
    {
      "type": "dir",
      "title": "[COLORwhite]BBC iPlayer[/COLOR]",
      "link": "plugin://plugin.video.iplayerwww"
    },
    {
      "type": "dir",
      "title": "[COLORwhite]Crackle TV[/COLOR]",
      "link": "plugin://plugin.video.crackle"
    },
    {
      "type": "dir",
      "title": "[COLORwhite]Free Sports[/COLOR]",
      "link": "https://mfirepo.github.io/hal/fsportz.json"
    },
    {
      "type": "dir",
      "title": "[COLORwhite]Music Channels[/COLOR]",
      "link": "https://mfirepo.github.io/hal/music.json"
    }
  ]
}
