{
  "items": [
 
	{
      "type": "item",
      "title": "Formula 1",
      "link": "https://inst1.ignores.top/js/sky-sports-f1-sky-f1/1/playlist.m3u8|Referer=https://vipstreams.in&Origin=https://vipstreams.in"
      
    },
	{
      "type": "item",
      "title": "UFC: Cannonier vs Imavov",
      "sportjetextractors": [
        "https://sportsurge.stream/embed/ufc.php"
      ]
    },
	{
      "type": "dir",
      "title": "UFC: Cannonier vs Imavov",
      "pvr_sport_search":"search/cannonier?include=17"
    },
	{
      "type": "item",
      "title": "Boxing: Zayas vs Teixeira",
      "sportjetextractors": [
        "https://sportsurge.stream/embed/boxing.php"
      ]
    },
	{
      "type": "dir",
      "title": "Boxing: Zayas vs Teixeira",
      "pvr_sport_search":"search/zayas?include=17"
    }
	
	
	
	
	
]

}
