{
  "items": [
 
	{
      "type": "item",
      "title": "Formula 1",
      "link": "https://inst1.ignores.top/js/sky-sports-f1-sky-f1/1/playlist.m3u8|Referer=https://vipstreams.in&Origin=https://vipstreams.in"
      
    },
	{
      "type": "item",
      "title": "Formula 1",
      "sportjetextractors": [
      "https://d.daddylivehd.sx/stream/stream-60.php"
      ]
    },
	{
      "type": "item",
      "title": "Olympiakos vs Fiorentina",
      "pvr_sport_search":"search/fiorentina?include=17"
    }
	
	
	
	
]

}